rce.py
evil_rce-1.0.0.dist-info/licenses/LICENSE
evil_rce-1.0.0.dist-info/METADATA
evil_rce-1.0.0.dist-info/WHEEL
evil_rce-1.0.0.dist-info/entry_points.txt
evil_rce-1.0.0.dist-info/top_level.txt
evil_rce-1.0.0.dist-info/RECORD
